{ "system.indexes":
	[ { "collection": "nodes", "key": { "_id": 1 } }
	, { "collection": "shadow", "key": { "_id": 1 } }
	, { "collection": "nodes", "key": { "subject": 1 }, "options": {"unique": true, "sparse": true}}
	, { "collection": "cache", "key": { "_id": 1 }}
	]
, "nodes":
	[
		{ "_id": {"$ObjectId":"4ebd46425bd820c984240d96"}
		, "subject": "http://magnode.org/MongoDBJSONSchema"
		, "type": [ "http://magnode.org/MongoDBJSONSchema", "http://localhost/MongoDBJSONSchemaTable" ]
		, "ViewTransform": {}
		, "label": "MongoDB JSON Schema"
		, "menu":
			{ "http://localhost/Menu_ManagementMenu":
				{ "title": "MongoDBJSONSchema"
				, "weight": -1
				}
			}
		, "permissions": {}
		, "schema":
			{ "type": "object"
			, "properties":
				{ "_id": { "type": "ObjectId", "readonly": true }
				, "subject": { "type": "string", "format": "uri" }
				, "type": { "type": "array", "widget": "array", "items": { "type": "string", "format": "uri" } }
				, "label": { "type": "string", "widget": "http://magnode.org/field/line" }
				, "schema": { "type": "object", "widget": "json", "default": {} }
				, "tablequery": { "type": "object", "widget": "json", "default": {} }
				, "ViewTransform": { "type": "object", "widget": "json", "default": {} }
				, "menu": { "type": "object", "widget": "json" }
				, "permissions": { "type": [ "object", "null" ], "widget": "json", "default": null }
				}
			, "put":
				{ "storeRevision": true
				}
			}
		, "tablequery": { "fields": [ "_id", "subject", "label" ] }
		}

	]
}
